Metadata-Version: 2.1
Name: social-auth-core-tweaked
Version: 4.4.2
Summary: Forked form social-auth-core to fix a bug with PYJWT
Home-page: https://github.com/python-social-auth/social-core
Author: Muyiwa ALASHI
Author-email: alashimuyiwa@gmail.com
License: BSD
Keywords: openid,oauth,saml,social auth
Classifier: Development Status :: 4 - Beta
Classifier: Topic :: Internet
Classifier: License :: OSI Approved :: BSD License
Classifier: Intended Audience :: Developers
Classifier: Environment :: Web Environment
Classifier: Programming Language :: Python
Classifier: Programming Language :: Python :: 3
Classifier: Programming Language :: Python :: 3.6
Classifier: Programming Language :: Python :: 3.7
Classifier: Programming Language :: Python :: 3.8
Classifier: Programming Language :: Python :: 3.9
Requires-Python: >=3.6
License-File: LICENSE
Requires-Dist: requests (>=2.9.1)
Requires-Dist: oauthlib (>=1.0.3)
Requires-Dist: requests-oauthlib (>=0.6.1)
Requires-Dist: PyJWT (>=1.7.0)
Requires-Dist: cryptography (>=1.4)
Requires-Dist: defusedxml (>=0.5.0rc1)
Requires-Dist: python3-openid (>=3.0.10)
Provides-Extra: all
Requires-Dist: python-jose (>=3.0.0) ; extra == 'all'
Requires-Dist: python3-saml (>=1.5.0) ; extra == 'all'
Requires-Dist: cryptography (>=2.1.1) ; extra == 'all'
Provides-Extra: allpy3
Requires-Dist: python-jose (>=3.0.0) ; extra == 'allpy3'
Requires-Dist: python3-saml (>=1.5.0) ; extra == 'allpy3'
Requires-Dist: cryptography (>=2.1.1) ; extra == 'allpy3'
Provides-Extra: azuread
Requires-Dist: cryptography (>=2.1.1) ; extra == 'azuread'
Provides-Extra: openidconnect
Requires-Dist: python-jose (>=3.0.0) ; extra == 'openidconnect'
Provides-Extra: saml
Requires-Dist: python3-saml (>=1.5.0) ; extra == 'saml'
